{
    "areas": [],
    "categories": [
        {
            "id": "ore",
            "name": "Ore Node",
            "color": "#f59e0b"
        },
        {
            "id": "herb",
            "name": "Herb Node",
            "color": "#22c55e"
        },
        {
            "id": "fates",
            "name": "Notorious monster",
            "group": "Fates",
            "groupName": "Fates2",
            "iconUrl": "https://v2.xivapi.com/api/asset/ui/icon/060000/060852.tex?format=webp"
        },
        {
            "id": "fates",
            "name": "Gegner Wellen",
            "group": "Fates",
            "groupName": "Fates2",
            "iconUrl": "https://v2.xivapi.com/api/asset/ui/icon/060000/060801.tex?format=webp"
        },
        {
            "id": "fates",
            "name": "Boss besiegen",
            "group": "Fates",
            "groupName": "Fates2",
            "iconUrl": "https://v2.xivapi.com/api/asset/ui/icon/060000/060802.tex?format=webp"
        },
        {
            "id": "fates",
            "name": "Sammeln",
            "group": "Fates",
            "groupName": "Fates2",
            "iconUrl": "https://v2.xivapi.com/api/asset/ui/icon/060000/060803.tex?format=webp"
        },
        {
            "id": "fates",
            "name": "Verteidigen",
            "group": "Fates",
            "groupName": "Fates2",
            "iconUrl": "https://v2.xivapi.com/api/asset/ui/icon/060000/060804.tex?format=webp"
        },
        {
            "id": "fates",
            "name": "NoType",
            "group": "Fates",
            "groupName": "Fates2",
            "iconUrl": "https://v2.xivapi.com/api/asset/ui/icon/000000/000000.tex?format=webp"
        },
        {
            "id": "kill_enemies",
            "name": "Kill Enemies",
            "group": "Fates",
            "groupName": "Fates2",
            "iconUrl": "https://v2.xivapi.com/api/asset/ui/icon/060000/060501.tex?format=webp"
        },
        {
            "id": "kill_boss",
            "name": "Kill Boss",
            "group": "Fates",
            "groupName": "Fates2",
            "iconUrl": "https://v2.xivapi.com/api/asset/ui/icon/060000/060502.tex?format=webp"
        },
        {
            "id": "collect",
            "name": "Collect",
            "group": "Fates",
            "groupName": "Fates2",
            "iconUrl": "https://v2.xivapi.com/api/asset/ui/icon/060000/060503.tex?format=webp"
        },
        {
            "id": "defense",
            "name": "Defense",
            "group": "Fates",
            "groupName": "Fates2",
            "iconUrl": "https://v2.xivapi.com/api/asset/ui/icon/060000/060504.tex?format=webp"
        },
        {
            "id": "fates",
            "name": "Escort",
            "group": "Fates",
            "groupName": "Fates2",
            "iconUrl": "https://v2.xivapi.com/api/asset/ui/icon/060000/060505.tex?format=webp"
        },
        {
            "id": "fates",
            "name": "Chase",
            "group": "Fates",
            "groupName": "Fates2",
            "iconUrl": "https://v2.xivapi.com/api/asset/ui/icon/060000/060506.tex?format=webp"
        },
        {
            "id": "fates",
            "name": "Holiday (Limited Time",
            "group": "Fates",
            "groupName": "Fates2",
            "iconUrl": "https://v2.xivapi.com/api/asset/ui/icon/060000/060508.tex?format=webp"
        },
        {
            "id": "fates",
            "name": "Concerted works",
            "group": "Fates",
            "groupName": "Fates2",
            "iconUrl": "https://v2.xivapi.com/api/asset/ui/icon/060000/060994.tex?format=webp"
        },
        {
            "id": "fates",
            "name": "Notorious monsters",
            "group": "Fates",
            "groupName": "Fates2",
            "iconUrl": "https://v2.xivapi.com/api/asset/ui/icon/060000/060958.tex?format=webp"
        },
        {
            "id": "fates",
            "name": "Fete",
            "group": "Fates",
            "groupName": "Fates2",
            "iconUrl": "https://v2.xivapi.com/api/asset/ui/icon/063000/063926.tex?format=webp"
        },
        {
            "id": "fates",
            "name": "CE Boss besiegen",
            "group": "Fates",
            "groupName": "Fates2",
            "iconUrl": "https://v2.xivapi.com/api/asset/ui/icon/063000/063909.tex?format=webp"
        },
        {
            "id": "fates",
            "name": "CE Solo Kampf",
            "group": "Fates",
            "groupName": "Fates2",
            "iconUrl": "https://v2.xivapi.com/api/asset/ui/icon/063000/063910.tex?format=webp"
        },
        {
            "id": "fates",
            "name": "CE Gegner Wellen",
            "group": "Fates",
            "groupName": "Fates2",
            "iconUrl": "https://v2.xivapi.com/api/asset/ui/icon/063000/063911.tex?format=web"
        },
        {
            "id": "gathering-zone",
            "name": "Gathering Zone",
            "color": "#FFc55e",
            "group": "Zones",
            "groupName": "Zones"
        },
        {
            "id": "treasuremap_vergilbte_lederkarte",
            "name": "Vergilbte Lederkarte",
            "group": "treasuremap",
            "groupName": "Schatzkarten",
            "color": "#22c55e"
        },
        {
            "id": "treasuremap_vergilbte_steinbockleder_karte",
            "name": "Vergilbte Steinbockleder-Karte",
            "group": "treasuremap",
            "groupName": "Schatzkarten",
            "color": "#22c55e"
        },
        {
            "id": "treasuremap_vergilbte_kroetenleder_karte",
            "name": "Vergilbte Krötenleder-Karte",
            "group": "treasuremap",
            "groupName": "Schatzkarten",
            "color": "#22c55e"
        },
        {
            "id": "treasuremap_vergilbte_keilerleder_karte",
            "name": "Vergilbte Keilerleder-Karte",
            "group": "treasuremap",
            "groupName": "Schatzkarten",
            "color": "#22c55e"
        },
        {
            "id": "treasuremap_vergilbte_basiliskenleder_karte",
            "name": "Vergilbte Basiliskenleder-Karte",
            "group": "treasuremap",
            "groupName": "Schatzkarten",
            "color": "#22c55e"
        },
        {
            "id": "treasuremap_geheimnisvolle_karte",
            "name": "Geheimnisvolle Karte",
            "group": "treasuremap",
            "groupName": "Schatzkarten",
            "color": "#22c55e"
        },
        {
            "id": "treasuremap_unversteckte_lederkarte",
            "name": "Unversteckte Lederkarte",
            "group": "treasuremap",
            "groupName": "Schatzkarten",
            "color": "#22c55e"
        },
        {
            "id": "treasuremap_schatzkarte_aus_der_thorne_aera",
            "name": "Schatzkarte aus der Thorne-Ära",
            "group": "treasuremap",
            "groupName": "Schatzkarten",
            "color": "#22c55e"
        },
        {
            "id": "treasuremap_vergilbte_archaeoleder_karte",
            "name": "Vergilbte Archaeoleder-Karte",
            "group": "treasuremap",
            "groupName": "Schatzkarten",
            "color": "#22c55e"
        },
        {
            "id": "treasuremap_vergilbte_wyvernleder_karte",
            "name": "Vergilbte Wyvernleder-Karte",
            "group": "treasuremap",
            "groupName": "Schatzkarten",
            "color": "#22c55e"
        },
        {
            "id": "treasuremap_vergilbte_drachenleder_karte",
            "name": "Vergilbte Drachenleder-Karte",
            "group": "treasuremap",
            "groupName": "Schatzkarten",
            "color": "#22c55e"
        },
        {
            "id": "treasuremap_vergilbte_gaganaleder_karte",
            "name": "Vergilbte Gaganaleder-Karte",
            "group": "treasuremap",
            "groupName": "Schatzkarten",
            "color": "#22c55e"
        },
        {
            "id": "treasuremap_vergilbte_gazellenleder_karte",
            "name": "Vergilbte Gazellenleder-Karte",
            "group": "treasuremap",
            "groupName": "Schatzkarten",
            "color": "#22c55e"
        },
        {
            "id": "treasuremap_vergilbte_schatzkarte_eines_meisterdiebes",
            "name": "Vergilbte Schatzkarte eines Meisterdiebes",
            "group": "treasuremap",
            "groupName": "Schatzkarten",
            "color": "#22c55e"
        },
        {
            "id": "treasuremap_vergilbte_exotenleder_karte",
            "name": "Vergilbte Exotenleder-Karte",
            "group": "treasuremap",
            "groupName": "Schatzkarten",
            "color": "#22c55e"
        },
        {
            "id": "treasuremap_vergilbte_smilodonleder_karte",
            "name": "Vergilbte Smilodonleder-Karte",
            "group": "treasuremap",
            "groupName": "Schatzkarten",
            "color": "#22c55e"
        },
        {
            "id": "treasuremap_vergilbte_glaucusleder_karte",
            "name": "Vergilbte Glaucusleder-Karte",
            "group": "treasuremap",
            "groupName": "Schatzkarten",
            "color": "#22c55e"
        },
        {
            "id": "treasuremap_vergilbte_mythenleder_karte",
            "name": "Vergilbte Mythenleder-Karte",
            "group": "treasuremap",
            "groupName": "Schatzkarten",
            "color": "#22c55e"
        },
        {
            "id": "treasuremap_vergilbte_gajaleder_schatzkarte",
            "name": "Vergilbte Gajaleder-Schatzkarte",
            "group": "treasuremap",
            "groupName": "Schatzkarten",
            "color": "#22c55e"
        },
        {
            "id": "treasuremap_vergilbte_kumbhilaleder_schatzkarte",
            "name": "Vergilbte Kumbhilaleder-Schatzkarte",
            "group": "treasuremap",
            "groupName": "Schatzkarten",
            "color": "#22c55e"
        },
        {
            "id": "treasuremap_vergilbte_ophiotaurosleder_schatzkarte",
            "name": "Vergilbte Ophiotaurosleder-Schatzkarte",
            "group": "treasuremap",
            "groupName": "Schatzkarten",
            "color": "#22c55e"
        },
        {
            "id": "treasuremap_vergilbte_legendenleder_karte",
            "name": "Vergilbte Legendenleder-Karte",
            "group": "treasuremap",
            "groupName": "Schatzkarten",
            "color": "#22c55e"
        },
        {
            "id": "treasuremap_vergilbte_sagenleder_karte",
            "name": "Vergilbte Sagenleder-Karte",
            "group": "treasuremap",
            "groupName": "Schatzkarten",
            "color": "#22c55e"
        },
        {
            "id": "treasuremap_vergilbte_schakalleder_schatzkarte",
            "name": "Vergilbte Schakalleder-Schatzkarte",
            "group": "treasuremap",
            "groupName": "Schatzkarten",
            "color": "#22c55e"
        },
        {
            "id": "treasuremap_vergilbte_braaxleder_schatzkarte",
            "name": "Vergilbte Br'aaxleder-Schatzkarte",
            "group": "treasuremap",
            "groupName": "Schatzkarten",
            "color": "#22c55e"
        },
        {
            "id": "treasuremap_vergilbte_gargantualeder_karte",
            "name": "Vergilbte Gargantualeder-Karte",
            "group": "treasuremap",
            "groupName": "Schatzkarten",
            "color": "#22c55e"
        }
    ],
    "defaultZoom": -1.2,
    "id": "central-thanalan",
    "imageUrl": "https://ff14.akurosiakamo.de/extras/images//ui/map/w1f/w1f2 - Zentrales Thanalan.png",
    "markers": [
        {
            "id": "1",
            "name": "Die mechanischen Krieger",
            "category": "kill_enemies",
            "position": [
                1315.72,
                1044.48
            ],
            "description": ""
        },
        {
            "id": "1",
            "name": "Hungriges Hirn",
            "category": "kill_enemies",
            "position": [
                1038.99,
                911.11
            ],
            "description": ""
        },
        {
            "id": "1",
            "name": "Blinde Wut",
            "category": "kill_enemies",
            "position": [
                890.63,
                1061.96
            ],
            "description": ""
        },
        {
            "id": "1",
            "name": "Wehe, wenn sie alleingelassen",
            "category": "kill_enemies",
            "position": [
                1385.65,
                1130.4
            ],
            "description": ""
        },
        {
            "id": "1",
            "name": "Alle Klauen voll zu tun",
            "category": "kill_enemies",
            "position": [
                866.65,
                1321.21
            ],
            "description": ""
        },
        {
            "id": "1",
            "name": "Seelenlose Grausamkeit",
            "category": "kill_enemies",
            "position": [
                729.79,
                992.53
            ],
            "description": ""
        },
        {
            "id": "1",
            "name": "Federfall-Quartier: 4. Phase - Beginn",
            "category": "kill_enemies",
            "position": [
                861.66,
                922.6
            ],
            "description": ""
        },
        {
            "id": "1",
            "name": "Wiederkehrende Bugs",
            "category": "kill_enemies",
            "position": [
                883.64,
                1306.72
            ],
            "description": ""
        },
        {
            "id": "1",
            "name": "Lockere Schrauben",
            "category": "kill_boss",
            "position": [
                1001.52,
                814.2
            ],
            "description": ""
        },
        {
            "id": "1",
            "name": "Der giftgrüne Daumen",
            "category": "kill_boss",
            "position": [
                775.74,
                1128.9
            ],
            "description": ""
        },
        {
            "id": "1",
            "name": "Der rotierende Turm von Azys Lla",
            "category": "kill_boss",
            "position": [
                1367.16,
                1111.91
            ],
            "description": ""
        },
        {
            "id": "1",
            "name": "Entmachtung der Königin",
            "category": "kill_boss",
            "position": [
                861.16,
                922.6
            ],
            "description": ""
        },
        {
            "id": "1",
            "name": "Zündeln verboten",
            "category": "kill_boss",
            "position": [
                810.21,
                1351.18
            ],
            "description": ""
        },
        {
            "id": "1",
            "name": "Empusen-Epidemie",
            "category": "defense",
            "position": [
                940.08,
                1075.95
            ],
            "description": ""
        },
        {
            "id": "1",
            "name": "Zurück zu den Toten",
            "category": "defense",
            "position": [
                1195.33,
                566.95
            ],
            "description": ""
        },
        {
            "id": "1",
            "name": "Das bleibt lieber vergessen",
            "category": "collect",
            "position": [
                1123.9,
                1230.8
            ],
            "description": ""
        },
        {
            "id": "1",
            "name": "Ernter des Todes",
            "category": "collect",
            "position": [
                1146.38,
                1070.95
            ],
            "description": ""
        },
        {
            "id": "1",
            "name": "Reis stampfen, Herzen erobern",
            "category": "collect",
            "position": [
                1191.34,
                567.95
            ],
            "description": ""
        },
        {
            "type": "treasuremap_vergilbte_lederkarte",
            "imageUrl": "/assets/img/TreasureMaps/Vergilbte Lederkarte/empty_map.webp",
            "size": [
                220,
                200
            ],
            "position": [
                1165.4,
                384.4
            ]
        },
        {
            "type": "treasuremap_vergilbte_lederkarte",
            "imageUrl": "/assets/img/TreasureMaps/Vergilbte Lederkarte/empty_map.webp",
            "size": [
                220,
                200
            ],
            "position": [
                1215.6,
                1195.5
            ]
        },
        {
            "type": "treasuremap_vergilbte_lederkarte",
            "imageUrl": "/assets/img/TreasureMaps/Vergilbte Lederkarte/empty_map.webp",
            "size": [
                220,
                200
            ],
            "position": [
                824.7,
                1148.1
            ]
        },
        {
            "type": "treasuremap_vergilbte_steinbockleder_karte",
            "imageUrl": "/assets/img/TreasureMaps/Vergilbte Steinbockleder-Karte/empty_map.webp",
            "size": [
                220,
                200
            ],
            "position": [
                984.9,
                1438.4
            ]
        },
        {
            "type": "treasuremap_vergilbte_steinbockleder_karte",
            "imageUrl": "/assets/img/TreasureMaps/Vergilbte Steinbockleder-Karte/empty_map.webp",
            "size": [
                220,
                200
            ],
            "position": [
                752.4,
                1082.8
            ]
        },
        {
            "type": "treasuremap_vergilbte_steinbockleder_karte",
            "imageUrl": "/assets/img/TreasureMaps/Vergilbte Steinbockleder-Karte/empty_map.webp",
            "size": [
                220,
                200
            ],
            "position": [
                1045.9,
                969.1
            ]
        },
        {
            "type": "treasuremap_vergilbte_kroetenleder_karte",
            "imageUrl": "/assets/img/TreasureMaps/Vergilbte Krötenleder-Karte/empty_map.webp",
            "size": [
                220,
                200
            ],
            "position": [
                853.9,
                1032.7
            ]
        },
        {
            "type": "treasuremap_vergilbte_kroetenleder_karte",
            "imageUrl": "/assets/img/TreasureMaps/Vergilbte Krötenleder-Karte/empty_map.webp",
            "size": [
                220,
                200
            ],
            "position": [
                1064.5,
                411.9
            ]
        },
        {
            "type": "treasuremap_vergilbte_kroetenleder_karte",
            "imageUrl": "/assets/img/TreasureMaps/Vergilbte Krötenleder-Karte/empty_map.webp",
            "size": [
                220,
                200
            ],
            "position": [
                867.0,
                1219.8
            ]
        },
        {
            "type": "treasuremap_vergilbte_keilerleder_karte",
            "imageUrl": "/assets/img/TreasureMaps/Vergilbte Keilerleder-Karte/empty_map.webp",
            "size": [
                220,
                200
            ],
            "position": [
                1324.0,
                1060.3
            ]
        },
        {
            "type": "treasuremap_vergilbte_keilerleder_karte",
            "imageUrl": "/assets/img/TreasureMaps/Vergilbte Keilerleder-Karte/empty_map.webp",
            "size": [
                220,
                200
            ],
            "position": [
                786.8,
                1282.5
            ]
        },
        {
            "type": "treasuremap_vergilbte_keilerleder_karte",
            "imageUrl": "/assets/img/TreasureMaps/Vergilbte Keilerleder-Karte/empty_map.webp",
            "size": [
                220,
                200
            ],
            "position": [
                1286.0,
                552.7
            ]
        },
        {
            "type": "treasuremap_vergilbte_basiliskenleder_karte",
            "imageUrl": "/assets/img/TreasureMaps/Vergilbte Basiliskenleder-Karte/empty_map.webp",
            "size": [
                220,
                200
            ],
            "position": [
                813.1,
                1468.0
            ]
        },
        {
            "type": "treasuremap_vergilbte_basiliskenleder_karte",
            "imageUrl": "/assets/img/TreasureMaps/Vergilbte Basiliskenleder-Karte/empty_map.webp",
            "size": [
                220,
                200
            ],
            "position": [
                766.6,
                938.4
            ]
        },
        {
            "type": "treasuremap_vergilbte_basiliskenleder_karte",
            "imageUrl": "/assets/img/TreasureMaps/Vergilbte Basiliskenleder-Karte/empty_map.webp",
            "size": [
                220,
                200
            ],
            "position": [
                1090.2,
                1123.4
            ]
        },
        {
            "type": "treasuremap_geheimnisvolle_karte",
            "imageUrl": "/assets/img/TreasureMaps/Geheimnisvolle Karte/empty_map.webp",
            "size": [
                220,
                200
            ],
            "position": [
                909.1,
                1421.8
            ]
        },
        {
            "type": "treasuremap_geheimnisvolle_karte",
            "imageUrl": "/assets/img/TreasureMaps/Geheimnisvolle Karte/empty_map.webp",
            "size": [
                220,
                200
            ],
            "position": [
                1435.3,
                1130.4
            ]
        },
        {
            "type": "treasuremap_unversteckte_lederkarte",
            "imageUrl": "/assets/img/TreasureMaps/Unversteckte Lederkarte/empty_map.webp",
            "size": [
                220,
                200
            ],
            "position": [
                1020.6,
                1336.5
            ]
        },
        {
            "type": "treasuremap_unversteckte_lederkarte",
            "imageUrl": "/assets/img/TreasureMaps/Unversteckte Lederkarte/empty_map.webp",
            "size": [
                220,
                200
            ],
            "position": [
                953.0,
                993.2
            ]
        },
        {
            "type": "treasuremap_schatzkarte_aus_der_thorne_aera",
            "imageUrl": "/assets/img/TreasureMaps/Schatzkarte aus der Thorne-Ära/empty_map.webp",
            "size": [
                220,
                200
            ],
            "position": [
                1233.5,
                1089.8
            ]
        },
        {
            "type": "treasuremap_schatzkarte_aus_der_thorne_aera",
            "imageUrl": "/assets/img/TreasureMaps/Schatzkarte aus der Thorne-Ära/empty_map.webp",
            "size": [
                220,
                200
            ],
            "position": [
                1124.7,
                611.2
            ]
        }
    ],
    "maxZoom": 1.7,
    "minZoom": -1.2,
    "name": "Central Thanalan",
    "size": [
        2048,
        2048
    ]
}